<?xml version="1.0"?>
<rolemap>
  <permissions>
    <permission acquire="False"
                name="ploneorg.core: Add Foundation Member"
    />
    <permission acquire="True"
                name="Add Plone Release"
    >
      <role name="Manager" />
    </permission>
    <permission acquire="True"
                name="ploneorg.core: View Foundation Member Details"
    >
      <role name="Manager" />
      <role name="Editor" />
      <role name="Owner" />
    </permission>
  </permissions>
</rolemap>
